{"weekDays":[{"line":"705","day":"weekDay","fwdHour":"05:40","bwdHour":"06:00","inId":"1"},{"line":"705","day":"weekDay","fwdHour":"06:00","bwdHour":"06:20","inId":"2"},{"line":"705","day":"weekDay","fwdHour":"06:20","bwdHour":"06:35","inId":"3"},{"line":"705","day":"weekDay","fwdHour":"06:35","bwdHour":"06:45","inId":"4"},{"line":"705","day":"weekDay","fwdHour":"06:45","bwdHour":"06:55","inId":"5"},{"line":"705","day":"weekDay","fwdHour":"06:55","bwdHour":"07:07","inId":"6"},{"line":"705","day":"weekDay","fwdHour":"07:05","bwdHour":"07:19","inId":"7"},{"line":"705","day":"weekDay","fwdHour":"07:14","bwdHour":"07:30","inId":"8"},{"line":"705","day":"weekDay","fwdHour":"07:27","bwdHour":"07:45","inId":"9"},{"line":"705","day":"weekDay","fwdHour":"07:40","bwdHour":"07:59","inId":"10"},{"line":"705","day":"weekDay","fwdHour":"07:53","bwdHour":"08:10","inId":"11"},{"line":"705","day":"weekDay","fwdHour":"08:06","bwdHour":"08:20","inId":"12"},{"line":"705","day":"weekDay","fwdHour":"08:20","bwdHour":"08:40","inId":"13"},{"line":"705","day":"weekDay","fwdHour":"08:40","bwdHour":"09:05","inId":"14"},{"line":"705","day":"weekDay","fwdHour":"09:05","bwdHour":"09:35","inId":"15"},{"line":"705","day":"weekDay","fwdHour":"09:25","bwdHour":"09:50","inId":"16"},{"line":"705","day":"weekDay","fwdHour":"09:50","bwdHour":"10:10","inId":"17"},{"line":"705","day":"weekDay","fwdHour":"10:14","bwdHour":"10:30","inId":"18"},{"line":"705","day":"weekDay","fwdHour":"10:33","bwdHour":"10:49","inId":"19"},{"line":"705","day":"weekDay","fwdHour":"10:51","bwdHour":"11:08","inId":"20"},{"line":"705","day":"weekDay","fwdHour":"11:10","bwdHour":"11:26","inId":"21"},{"line":"705","day":"weekDay","fwdHour":"11:29","bwdHour":"11:45","inId":"22"},{"line":"705","day":"weekDay","fwdHour":"11:48","bwdHour":"12:04","inId":"23"},{"line":"705","day":"weekDay","fwdHour":"12:11","bwdHour":"12:23","inId":"24"},{"line":"705","day":"weekDay","fwdHour":"12:30","bwdHour":"12:42","inId":"25"},{"line":"705","day":"weekDay","fwdHour":"12:51","bwdHour":"13:05","inId":"26"},{"line":"705","day":"weekDay","fwdHour":"13:20","bwdHour":"13:30","inId":"27"},{"line":"705","day":"weekDay","fwdHour":"13:35","bwdHour":"14:00","inId":"28"},{"line":"705","day":"weekDay","fwdHour":"13:54","bwdHour":"14:15","inId":"29"},{"line":"705","day":"weekDay","fwdHour":"14:15","bwdHour":"14:36","inId":"30"},{"line":"705","day":"weekDay","fwdHour":"14:36","bwdHour":"14:57","inId":"31"},{"line":"705","day":"weekDay","fwdHour":"14:57","bwdHour":"15:18","inId":"32"},{"line":"705","day":"weekDay","fwdHour":"15:18","bwdHour":"15:39","inId":"33"},{"line":"705","day":"weekDay","fwdHour":"15:39","bwdHour":"16:05","inId":"34"},{"line":"705","day":"weekDay","fwdHour":"16:05","bwdHour":"16:29","inId":"35"},{"line":"705","day":"weekDay","fwdHour":"16:30","bwdHour":"16:53","inId":"36"},{"line":"705","day":"weekDay","fwdHour":"16:55","bwdHour":"17:05","inId":"37"},{"line":"705","day":"weekDay","fwdHour":"17:10","bwdHour":"17:17","inId":"38"},{"line":"705","day":"weekDay","fwdHour":"17:28","bwdHour":"17:29","inId":"39"},{"line":"705","day":"weekDay","fwdHour":"17:40","bwdHour":"17:41","inId":"40"},{"line":"705","day":"weekDay","fwdHour":"17:52","bwdHour":"17:53","inId":"41"},{"line":"705","day":"weekDay","fwdHour":"18:04","bwdHour":"18:05","inId":"42"},{"line":"705","day":"weekDay","fwdHour":"18:16","bwdHour":"18:17","inId":"43"},{"line":"705","day":"weekDay","fwdHour":"18:28","bwdHour":"18:29","inId":"44"},{"line":"705","day":"weekDay","fwdHour":"18:40","bwdHour":"18:41","inId":"45"},{"line":"705","day":"weekDay","fwdHour":"18:50","bwdHour":"18:53","inId":"46"},{"line":"705","day":"weekDay","fwdHour":"19:00","bwdHour":"19:05","inId":"47"},{"line":"705","day":"weekDay","fwdHour":"19:10","bwdHour":"19:17","inId":"48"},{"line":"705","day":"weekDay","fwdHour":"19:20","bwdHour":"19:29","inId":"49"},{"line":"705","day":"weekDay","fwdHour":"19:30","bwdHour":"19:41","inId":"50"},{"line":"705","day":"weekDay","fwdHour":"19:40","bwdHour":"19:53","inId":"51"},{"line":"705","day":"weekDay","fwdHour":"20:05","bwdHour":"20:10","inId":"52"},{"line":"705","day":"weekDay","fwdHour":"20:30","bwdHour":"20:37","inId":"53"},{"line":"705","day":"weekDay","fwdHour":"20:51","bwdHour":"21:04","inId":"54"},{"line":"705","day":"weekDay","fwdHour":"21:18","bwdHour":"21:31","inId":"55"},{"line":"705","day":"weekDay","fwdHour":"21:45","bwdHour":"21:58","inId":"56"},{"line":"705","day":"weekDay","fwdHour":"22:12","bwdHour":"22:25","inId":"57"},{"line":"705","day":"weekDay","fwdHour":"22:39","bwdHour":"22:52","inId":"58"},{"line":"705","day":"weekDay","fwdHour":"23:06","bwdHour":"23:15","inId":"59"},{"line":"705","day":"weekDay","fwdHour":"23:33","bwdHour":"23:30","inId":"60"},{"line":"705","day":"weekDay","fwdHour":"00:05","bwdHour":"23:46","inId":"61"},{"line":"705","day":"weekDay","fwdHour":"","bwdHour":"00:10","inId":"62"}],"saturdays":[{"line":"705","day":"saturday","fwdHour":"05:40","bwdHour":"06:00","inId":"1"},{"line":"705","day":"saturday","fwdHour":"06:00","bwdHour":"06:20","inId":"2"},{"line":"705","day":"saturday","fwdHour":"06:20","bwdHour":"06:40","inId":"3"},{"line":"705","day":"saturday","fwdHour":"06:35","bwdHour":"06:53","inId":"4"},{"line":"705","day":"saturday","fwdHour":"06:50","bwdHour":"07:06","inId":"5"},{"line":"705","day":"saturday","fwdHour":"07:05","bwdHour":"07:20","inId":"6"},{"line":"705","day":"saturday","fwdHour":"07:20","bwdHour":"07:30","inId":"7"},{"line":"705","day":"saturday","fwdHour":"07:33","bwdHour":"07:40","inId":"8"},{"line":"705","day":"saturday","fwdHour":"07:46","bwdHour":"07:50","inId":"9"},{"line":"705","day":"saturday","fwdHour":"08:00","bwdHour":"08:00","inId":"10"},{"line":"705","day":"saturday","fwdHour":"08:20","bwdHour":"08:13","inId":"11"},{"line":"705","day":"saturday","fwdHour":"08:40","bwdHour":"08:26","inId":"12"},{"line":"705","day":"saturday","fwdHour":"09:08","bwdHour":"08:52","inId":"13"},{"line":"705","day":"saturday","fwdHour":"09:34","bwdHour":"09:18","inId":"14"},{"line":"705","day":"saturday","fwdHour":"10:00","bwdHour":"09:44","inId":"15"},{"line":"705","day":"saturday","fwdHour":"10:26","bwdHour":"10:10","inId":"16"},{"line":"705","day":"saturday","fwdHour":"10:52","bwdHour":"10:36","inId":"17"},{"line":"705","day":"saturday","fwdHour":"11:18","bwdHour":"11:00","inId":"18"},{"line":"705","day":"saturday","fwdHour":"11:44","bwdHour":"11:21","inId":"19"},{"line":"705","day":"saturday","fwdHour":"12:05","bwdHour":"11:42","inId":"20"},{"line":"705","day":"saturday","fwdHour":"12:26","bwdHour":"12:03","inId":"21"},{"line":"705","day":"saturday","fwdHour":"12:47","bwdHour":"12:24","inId":"22"},{"line":"705","day":"saturday","fwdHour":"13:08","bwdHour":"12:45","inId":"23"},{"line":"705","day":"saturday","fwdHour":"13:29","bwdHour":"13:06","inId":"24"},{"line":"705","day":"saturday","fwdHour":"13:50","bwdHour":"13:27","inId":"25"},{"line":"705","day":"saturday","fwdHour":"14:11","bwdHour":"13:48","inId":"26"},{"line":"705","day":"saturday","fwdHour":"14:32","bwdHour":"14:09","inId":"27"},{"line":"705","day":"saturday","fwdHour":"14:53","bwdHour":"14:30","inId":"28"},{"line":"705","day":"saturday","fwdHour":"15:05","bwdHour":"14:52","inId":"29"},{"line":"705","day":"saturday","fwdHour":"15:17","bwdHour":"15:14","inId":"30"},{"line":"705","day":"saturday","fwdHour":"15:35","bwdHour":"15:36","inId":"31"},{"line":"705","day":"saturday","fwdHour":"15:55","bwdHour":"15:58","inId":"32"},{"line":"705","day":"saturday","fwdHour":"16:20","bwdHour":"16:18","inId":"33"},{"line":"705","day":"saturday","fwdHour":"16:45","bwdHour":"16:36","inId":"34"},{"line":"705","day":"saturday","fwdHour":"17:03","bwdHour":"16:54","inId":"35"},{"line":"705","day":"saturday","fwdHour":"17:21","bwdHour":"17:12","inId":"36"},{"line":"705","day":"saturday","fwdHour":"17:39","bwdHour":"17:30","inId":"37"},{"line":"705","day":"saturday","fwdHour":"17:57","bwdHour":"17:48","inId":"38"},{"line":"705","day":"saturday","fwdHour":"18:15","bwdHour":"18:06","inId":"39"},{"line":"705","day":"saturday","fwdHour":"18:33","bwdHour":"18:24","inId":"40"},{"line":"705","day":"saturday","fwdHour":"18:51","bwdHour":"18:42","inId":"41"},{"line":"705","day":"saturday","fwdHour":"19:09","bwdHour":"19:00","inId":"42"},{"line":"705","day":"saturday","fwdHour":"19:27","bwdHour":"19:18","inId":"43"},{"line":"705","day":"saturday","fwdHour":"19:45","bwdHour":"19:45","inId":"44"},{"line":"705","day":"saturday","fwdHour":"20:03","bwdHour":"20:12","inId":"45"},{"line":"705","day":"saturday","fwdHour":"20:26","bwdHour":"20:39","inId":"46"},{"line":"705","day":"saturday","fwdHour":"20:53","bwdHour":"21:06","inId":"47"},{"line":"705","day":"saturday","fwdHour":"21:20","bwdHour":"21:33","inId":"48"},{"line":"705","day":"saturday","fwdHour":"22:00","bwdHour":"22:00","inId":"49"},{"line":"705","day":"saturday","fwdHour":"22:40","bwdHour":"22:45","inId":"50"},{"line":"705","day":"saturday","fwdHour":"23:20","bwdHour":"23:10","inId":"51"},{"line":"705","day":"saturday","fwdHour":"00:05","bwdHour":"23:30","inId":"52"},{"line":"705","day":"saturday","fwdHour":"","bwdHour":"00:10","inId":"53"}],"sundays":[{"line":"705","day":"sunday","fwdHour":"06:00","bwdHour":"06:40","inId":"1"},{"line":"705","day":"sunday","fwdHour":"06:40","bwdHour":"07:20","inId":"2"},{"line":"705","day":"sunday","fwdHour":"07:20","bwdHour":"07:55","inId":"3"},{"line":"705","day":"sunday","fwdHour":"08:00","bwdHour":"08:20","inId":"4"},{"line":"705","day":"sunday","fwdHour":"08:30","bwdHour":"08:35","inId":"5"},{"line":"705","day":"sunday","fwdHour":"09:00","bwdHour":"09:20","inId":"6"},{"line":"705","day":"sunday","fwdHour":"09:30","bwdHour":"09:50","inId":"7"},{"line":"705","day":"sunday","fwdHour":"10:00","bwdHour":"10:15","inId":"8"},{"line":"705","day":"sunday","fwdHour":"10:26","bwdHour":"10:40","inId":"9"},{"line":"705","day":"sunday","fwdHour":"10:52","bwdHour":"11:04","inId":"10"},{"line":"705","day":"sunday","fwdHour":"11:14","bwdHour":"11:28","inId":"11"},{"line":"705","day":"sunday","fwdHour":"11:44","bwdHour":"11:54","inId":"12"},{"line":"705","day":"sunday","fwdHour":"12:10","bwdHour":"12:20","inId":"13"},{"line":"705","day":"sunday","fwdHour":"12:36","bwdHour":"12:46","inId":"14"},{"line":"705","day":"sunday","fwdHour":"13:02","bwdHour":"13:14","inId":"15"},{"line":"705","day":"sunday","fwdHour":"13:30","bwdHour":"13:42","inId":"16"},{"line":"705","day":"sunday","fwdHour":"13:58","bwdHour":"14:10","inId":"17"},{"line":"705","day":"sunday","fwdHour":"14:26","bwdHour":"14:38","inId":"18"},{"line":"705","day":"sunday","fwdHour":"14:54","bwdHour":"15:06","inId":"19"},{"line":"705","day":"sunday","fwdHour":"15:22","bwdHour":"15:34","inId":"20"},{"line":"705","day":"sunday","fwdHour":"15:50","bwdHour":"16:02","inId":"21"},{"line":"705","day":"sunday","fwdHour":"16:18","bwdHour":"16:30","inId":"22"},{"line":"705","day":"sunday","fwdHour":"16:46","bwdHour":"16:58","inId":"23"},{"line":"705","day":"sunday","fwdHour":"17:14","bwdHour":"17:26","inId":"24"},{"line":"705","day":"sunday","fwdHour":"17:42","bwdHour":"17:54","inId":"25"},{"line":"705","day":"sunday","fwdHour":"18:10","bwdHour":"18:22","inId":"26"},{"line":"705","day":"sunday","fwdHour":"18:40","bwdHour":"18:50","inId":"27"},{"line":"705","day":"sunday","fwdHour":"19:20","bwdHour":"19:20","inId":"28"},{"line":"705","day":"sunday","fwdHour":"20:00","bwdHour":"20:00","inId":"29"},{"line":"705","day":"sunday","fwdHour":"20:40","bwdHour":"20:40","inId":"30"},{"line":"705","day":"sunday","fwdHour":"21:20","bwdHour":"21:20","inId":"31"},{"line":"705","day":"sunday","fwdHour":"22:00","bwdHour":"22:00","inId":"32"},{"line":"705","day":"sunday","fwdHour":"22:40","bwdHour":"22:45","inId":"33"},{"line":"705","day":"sunday","fwdHour":"23:20","bwdHour":"23:10","inId":"34"},{"line":"705","day":"sunday","fwdHour":"00:05","bwdHour":"23:30","inId":"35"},{"line":"705","day":"sunday","fwdHour":"","bwdHour":"00:10","inId":"36"}]}