{"weekDays":[{"line":"751","day":"weekDay","fwdHour":"06:00","bwdHour":"06:10","inId":"1"},{"line":"751","day":"weekDay","fwdHour":"06:15","bwdHour":"06:25","inId":"2"},{"line":"751","day":"weekDay","fwdHour":"06:30","bwdHour":"06:40","inId":"3"},{"line":"751","day":"weekDay","fwdHour":"06:45","bwdHour":"06:55","inId":"4"},{"line":"751","day":"weekDay","fwdHour":"07:00","bwdHour":"07:10","inId":"5"},{"line":"751","day":"weekDay","fwdHour":"07:10","bwdHour":"07:20","inId":"6"},{"line":"751","day":"weekDay","fwdHour":"07:20","bwdHour":"07:30","inId":"7"},{"line":"751","day":"weekDay","fwdHour":"07:30","bwdHour":"07:40","inId":"8"},{"line":"751","day":"weekDay","fwdHour":"07:40","bwdHour":"07:50","inId":"9"},{"line":"751","day":"weekDay","fwdHour":"07:50","bwdHour":"08:00","inId":"10"},{"line":"751","day":"weekDay","fwdHour":"08:00","bwdHour":"08:10","inId":"11"},{"line":"751","day":"weekDay","fwdHour":"08:10","bwdHour":"08:20","inId":"12"},{"line":"751","day":"weekDay","fwdHour":"08:20","bwdHour":"08:35","inId":"13"},{"line":"751","day":"weekDay","fwdHour":"08:30","bwdHour":"08:40","inId":"14"},{"line":"751","day":"weekDay","fwdHour":"09:00","bwdHour":"08:50","inId":"15"},{"line":"751","day":"weekDay","fwdHour":"09:35","bwdHour":"09:20","inId":"16"},{"line":"751","day":"weekDay","fwdHour":"10:10","bwdHour":"09:55","inId":"17"},{"line":"751","day":"weekDay","fwdHour":"10:45","bwdHour":"10:30","inId":"18"},{"line":"751","day":"weekDay","fwdHour":"11:20","bwdHour":"11:05","inId":"19"},{"line":"751","day":"weekDay","fwdHour":"11:55","bwdHour":"11:40","inId":"20"},{"line":"751","day":"weekDay","fwdHour":"12:30","bwdHour":"12:15","inId":"21"},{"line":"751","day":"weekDay","fwdHour":"13:05","bwdHour":"12:50","inId":"22"},{"line":"751","day":"weekDay","fwdHour":"13:40","bwdHour":"13:25","inId":"23"},{"line":"751","day":"weekDay","fwdHour":"14:15","bwdHour":"14:00","inId":"24"},{"line":"751","day":"weekDay","fwdHour":"14:50","bwdHour":"14:35","inId":"25"},{"line":"751","day":"weekDay","fwdHour":"15:10","bwdHour":"15:10","inId":"26"},{"line":"751","day":"weekDay","fwdHour":"15:25","bwdHour":"15:45","inId":"27"},{"line":"751","day":"weekDay","fwdHour":"16:00","bwdHour":"16:20","inId":"28"},{"line":"751","day":"weekDay","fwdHour":"16:20","bwdHour":"16:55","inId":"29"},{"line":"751","day":"weekDay","fwdHour":"16:40","bwdHour":"17:16","inId":"30"},{"line":"751","day":"weekDay","fwdHour":"17:00","bwdHour":"17:38","inId":"31"},{"line":"751","day":"weekDay","fwdHour":"17:25","bwdHour":"18:00","inId":"32"},{"line":"751","day":"weekDay","fwdHour":"17:45","bwdHour":"18:20","inId":"33"},{"line":"751","day":"weekDay","fwdHour":"18:06","bwdHour":"18:40","inId":"34"},{"line":"751","day":"weekDay","fwdHour":"18:27","bwdHour":"19:00","inId":"35"},{"line":"751","day":"weekDay","fwdHour":"18:48","bwdHour":"19:20","inId":"36"},{"line":"751","day":"weekDay","fwdHour":"19:15","bwdHour":"19:40","inId":"37"},{"line":"751","day":"weekDay","fwdHour":"19:40","bwdHour":"20:20","inId":"38"},{"line":"751","day":"weekDay","fwdHour":"20:20","bwdHour":"21:10","inId":"39"},{"line":"751","day":"weekDay","fwdHour":"21:00","bwdHour":"21:50","inId":"40"},{"line":"751","day":"weekDay","fwdHour":"21:50","bwdHour":"22:40","inId":"41"},{"line":"751","day":"weekDay","fwdHour":"22:30","bwdHour":"23:20","inId":"42"},{"line":"751","day":"weekDay","fwdHour":"23:20","bwdHour":"00:00","inId":"43"}],"saturdays":[{"line":"751","day":"saturday","fwdHour":"06:00","bwdHour":"06:35","inId":"1"},{"line":"751","day":"saturday","fwdHour":"06:25","bwdHour":"07:00","inId":"2"},{"line":"751","day":"saturday","fwdHour":"06:50","bwdHour":"07:30","inId":"3"},{"line":"751","day":"saturday","fwdHour":"07:15","bwdHour":"08:00","inId":"4"},{"line":"751","day":"saturday","fwdHour":"07:45","bwdHour":"08:30","inId":"5"},{"line":"751","day":"saturday","fwdHour":"08:15","bwdHour":"09:00","inId":"6"},{"line":"751","day":"saturday","fwdHour":"08:45","bwdHour":"09:30","inId":"7"},{"line":"751","day":"saturday","fwdHour":"09:15","bwdHour":"10:00","inId":"8"},{"line":"751","day":"saturday","fwdHour":"09:45","bwdHour":"10:30","inId":"9"},{"line":"751","day":"saturday","fwdHour":"10:15","bwdHour":"11:00","inId":"10"},{"line":"751","day":"saturday","fwdHour":"10:45","bwdHour":"11:30","inId":"11"},{"line":"751","day":"saturday","fwdHour":"11:15","bwdHour":"12:00","inId":"12"},{"line":"751","day":"saturday","fwdHour":"11:45","bwdHour":"12:35","inId":"13"},{"line":"751","day":"saturday","fwdHour":"12:20","bwdHour":"13:10","inId":"14"},{"line":"751","day":"saturday","fwdHour":"12:55","bwdHour":"13:45","inId":"15"},{"line":"751","day":"saturday","fwdHour":"13:30","bwdHour":"14:20","inId":"16"},{"line":"751","day":"saturday","fwdHour":"14:05","bwdHour":"14:55","inId":"17"},{"line":"751","day":"saturday","fwdHour":"14:40","bwdHour":"15:30","inId":"18"},{"line":"751","day":"saturday","fwdHour":"15:15","bwdHour":"16:05","inId":"19"},{"line":"751","day":"saturday","fwdHour":"15:50","bwdHour":"16:40","inId":"20"},{"line":"751","day":"saturday","fwdHour":"16:25","bwdHour":"17:15","inId":"21"},{"line":"751","day":"saturday","fwdHour":"17:00","bwdHour":"17:50","inId":"22"},{"line":"751","day":"saturday","fwdHour":"17:35","bwdHour":"18:25","inId":"23"},{"line":"751","day":"saturday","fwdHour":"18:10","bwdHour":"19:00","inId":"24"},{"line":"751","day":"saturday","fwdHour":"18:45","bwdHour":"19:35","inId":"25"},{"line":"751","day":"saturday","fwdHour":"19:20","bwdHour":"20:10","inId":"26"},{"line":"751","day":"saturday","fwdHour":"20:00","bwdHour":"20:40","inId":"27"},{"line":"751","day":"saturday","fwdHour":"20:40","bwdHour":"21:20","inId":"28"},{"line":"751","day":"saturday","fwdHour":"21:20","bwdHour":"22:00","inId":"29"},{"line":"751","day":"saturday","fwdHour":"22:00","bwdHour":"22:40","inId":"30"},{"line":"751","day":"saturday","fwdHour":"22:40","bwdHour":"23:20","inId":"31"},{"line":"751","day":"saturday","fwdHour":"23:20","bwdHour":"00:00","inId":"32"}],"sundays":[{"line":"751","day":"sunday","fwdHour":"06:25","bwdHour":"07:00","inId":"1"},{"line":"751","day":"sunday","fwdHour":"07:00","bwdHour":"07:45","inId":"2"},{"line":"751","day":"sunday","fwdHour":"07:45","bwdHour":"08:30","inId":"3"},{"line":"751","day":"sunday","fwdHour":"08:30","bwdHour":"09:15","inId":"4"},{"line":"751","day":"sunday","fwdHour":"09:10","bwdHour":"10:00","inId":"5"},{"line":"751","day":"sunday","fwdHour":"09:40","bwdHour":"10:30","inId":"6"},{"line":"751","day":"sunday","fwdHour":"10:10","bwdHour":"11:00","inId":"7"},{"line":"751","day":"sunday","fwdHour":"10:45","bwdHour":"11:30","inId":"8"},{"line":"751","day":"sunday","fwdHour":"11:15","bwdHour":"12:00","inId":"9"},{"line":"751","day":"sunday","fwdHour":"11:45","bwdHour":"12:35","inId":"10"},{"line":"751","day":"sunday","fwdHour":"12:20","bwdHour":"13:10","inId":"11"},{"line":"751","day":"sunday","fwdHour":"12:55","bwdHour":"13:45","inId":"12"},{"line":"751","day":"sunday","fwdHour":"13:30","bwdHour":"14:20","inId":"13"},{"line":"751","day":"sunday","fwdHour":"14:05","bwdHour":"14:55","inId":"14"},{"line":"751","day":"sunday","fwdHour":"14:40","bwdHour":"15:30","inId":"15"},{"line":"751","day":"sunday","fwdHour":"15:15","bwdHour":"16:05","inId":"16"},{"line":"751","day":"sunday","fwdHour":"15:50","bwdHour":"16:40","inId":"17"},{"line":"751","day":"sunday","fwdHour":"16:25","bwdHour":"17:15","inId":"18"},{"line":"751","day":"sunday","fwdHour":"17:00","bwdHour":"17:50","inId":"19"},{"line":"751","day":"sunday","fwdHour":"17:35","bwdHour":"18:25","inId":"20"},{"line":"751","day":"sunday","fwdHour":"18:10","bwdHour":"19:00","inId":"21"},{"line":"751","day":"sunday","fwdHour":"18:45","bwdHour":"19:35","inId":"22"},{"line":"751","day":"sunday","fwdHour":"19:20","bwdHour":"20:10","inId":"23"},{"line":"751","day":"sunday","fwdHour":"20:00","bwdHour":"20:40","inId":"24"},{"line":"751","day":"sunday","fwdHour":"20:40","bwdHour":"21:20","inId":"25"},{"line":"751","day":"sunday","fwdHour":"21:20","bwdHour":"22:00","inId":"26"},{"line":"751","day":"sunday","fwdHour":"22:00","bwdHour":"22:40","inId":"27"},{"line":"751","day":"sunday","fwdHour":"22:40","bwdHour":"23:20","inId":"28"},{"line":"751","day":"sunday","fwdHour":"23:20","bwdHour":"00:00","inId":"29"}]}